octostar_streamlit/__init__.py
octostar_streamlit/components.py
octostar_streamlit/context.py
octostar_streamlit/core/__init__.py
octostar_streamlit/core/components/__init__.py
octostar_streamlit/core/components/method_call.py
octostar_streamlit/core/components/params.py
octostar_streamlit/core/context/__init__.py
octostar_streamlit/core/context/method_call.py
octostar_streamlit/core/context/params.py
octostar_streamlit/core/desktop/__init__.py
octostar_streamlit/core/desktop/method_call.py
octostar_streamlit/core/desktop/params.py
octostar_streamlit/core/entities.py
octostar_streamlit/core/extras/__init__.py
octostar_streamlit/core/extras/method_call.py
octostar_streamlit/core/extras/params.py
octostar_streamlit/core/method_call.py
octostar_streamlit/core/ontology/__init__.py
octostar_streamlit/core/ontology/method_call.py
octostar_streamlit/core/ontology/params.py
octostar_streamlit/core/params_base_model.py
octostar_streamlit/core/remote_app/__init__.py
octostar_streamlit/core/remote_app/method_call.py
octostar_streamlit/core/remote_app/params.py
octostar_streamlit/core/saved_search/__init__.py
octostar_streamlit/core/saved_search/method_call.py
octostar_streamlit/core/saved_search/params.py
octostar_streamlit/core/streamlit_executor.py
octostar_streamlit/desktop.py
octostar_streamlit/extras.py
octostar_streamlit/frontend/.gitignore
octostar_streamlit/frontend/.nvmrc
octostar_streamlit/frontend/dist/assets/index-BfyFBhHn.css
octostar_streamlit/frontend/dist/assets/index-DJ2mgocT.js
octostar_streamlit/frontend/dist/index.html
octostar_streamlit/frontend/dist/vite.svg
octostar_streamlit/frontend/index.html
octostar_streamlit/frontend/package-lock.json
octostar_streamlit/frontend/package.json
octostar_streamlit/frontend/public/vite.svg
octostar_streamlit/frontend/src/components/Button.less
octostar_streamlit/frontend/src/components/ComponentRenderer.tsx
octostar_streamlit/frontend/src/components/GetSearchResults.tsx
octostar_streamlit-0.1.27.dist-info/LICENSE
octostar_streamlit-0.1.27.dist-info/METADATA
octostar_streamlit-0.1.27.dist-info/WHEEL
octostar_streamlit-0.1.27.dist-info/RECORD
